python_vuetify_markdown/__init__.py
python_vuetify_markdown/python_vuetify_markdown.py
PythonVuetifyMarkdown-0.1.3.dist-info/LICENSE
PythonVuetifyMarkdown-0.1.3.dist-info/METADATA
PythonVuetifyMarkdown-0.1.3.dist-info/WHEEL
PythonVuetifyMarkdown-0.1.3.dist-info/top_level.txt
PythonVuetifyMarkdown-0.1.3.dist-info/RECORD
