Metadata-Version: 2.1
Name: PythonVuetifyMarkdown
Version: 0.1.3
Summary: Adds Vuetify typography classes to various tags
Home-page: https://gitlab.com/robertjauss/python-vuetify-markdown
Author: Robert Jauss
Author-email: robertjauss@gmail.com
License: UNKNOWN
Platform: UNKNOWN
Classifier: Programming Language :: Python :: 3
Classifier: License :: OSI Approved :: MIT License
Classifier: Operating System :: OS Independent
Requires-Python: >=3.4
Requires-Dist: markdown (>=2.5)
